{"ObjectStates":[{"Name":"DeckCustom","ContainedObjects":[{"CardID":100,"Name":"Card","Nickname":"Mountain","Transform":{"posX":0,"posY":0,"posZ":0,"rotX":0,"rotY":180,"rotZ":180,"scaleX":1,"scaleY":1,"scaleZ":1}},{"CardID":100,"Name":"Card","Nickname":"Mountain","Transform":{"posX":0,"posY":0,"posZ":0,"rotX":0,"rotY":180,"rotZ":180,"scaleX":1,"scaleY":1,"scaleZ":1}},{"CardID":100,"Name":"Card","Nickname":"Mountain","Transform":{"posX":0,"posY":0,"posZ":0,"rotX":0,"rotY":180,"rotZ":180,"scaleX":1,"scaleY":1,"scaleZ":1}},{"CardID":100,"Name":"Card","Nickname":"Mountain","Transform":{"posX":0,"posY":0,"posZ":0,"rotX":0,"rotY":180,"rotZ":180,"scaleX":1,"scaleY":1,"scaleZ":1}},{"CardID":100,"Name":"Card","Nickname":"Mountain","Transform":{"posX":0,"posY":0,"posZ":0,"rotX":0,"rotY":180,"rotZ":180,"scaleX":1,"scaleY":1,"scaleZ":1}},{"CardID":100,"Name":"Card","Nickname":"Mountain","Transform":{"posX":0,"posY":0,"posZ":0,"rotX":0,"rotY":180,"rotZ":180,"scaleX":1,"scaleY":1,"scaleZ":1}},{"CardID":100,"Name":"Card","Nickname":"Mountain","Transform":{"posX":0,"posY":0,"posZ":0,"rotX":0,"rotY":180,"rotZ":180,"scaleX":1,"scaleY":1,"scaleZ":1}},{"CardID":100,"Name":"Card","Nickname":"Mountain","Transform":{"posX":0,"posY":0,"posZ":0,"rotX":0,"rotY":180,"rotZ":180,"scaleX":1,"scaleY":1,"scaleZ":1}},{"CardID":100,"Name":"Card","Nickname":"Mountain","Transform":{"posX":0,"posY":0,"posZ":0,"rotX":0,"rotY":180,"rotZ":180,"scaleX":1,"scaleY":1,"scaleZ":1}},{"CardID":100,"Name":"Card","Nickname":"Mountain","Transform":{"posX":0,"posY":0,"posZ":0,"rotX":0,"rotY":180,"rotZ":180,"scaleX":1,"scaleY":1,"scaleZ":1}},{"CardID":100,"Name":"Card","Nickname":"Mountain","Transform":{"posX":0,"posY":0,"posZ":0,"rotX":0,"rotY":180,"rotZ":180,"scaleX":1,"scaleY":1,"scaleZ":1}},{"CardID":100,"Name":"Card","Nickname":"Mountain","Transform":{"posX":0,"posY":0,"posZ":0,"rotX":0,"rotY":180,"rotZ":180,"scaleX":1,"scaleY":1,"scaleZ":1}},{"CardID":100,"Name":"Card","Nickname":"Mountain","Transform":{"posX":0,"posY":0,"posZ":0,"rotX":0,"rotY":180,"rotZ":180,"scaleX":1,"scaleY":1,"scaleZ":1}},{"CardID":100,"Name":"Card","Nickname":"Mountain","Transform":{"posX":0,"posY":0,"posZ":0,"rotX":0,"rotY":180,"rotZ":180,"scaleX":1,"scaleY":1,"scaleZ":1}},{"CardID":100,"Name":"Card","Nickname":"Mountain","Transform":{"posX":0,"posY":0,"posZ":0,"rotX":0,"rotY":180,"rotZ":180,"scaleX":1,"scaleY":1,"scaleZ":1}},{"CardID":100,"Name":"Card","Nickname":"Mountain","Transform":{"posX":0,"posY":0,"posZ":0,"rotX":0,"rotY":180,"rotZ":180,"scaleX":1,"scaleY":1,"scaleZ":1}},{"CardID":100,"Name":"Card","Nickname":"Mountain","Transform":{"posX":0,"posY":0,"posZ":0,"rotX":0,"rotY":180,"rotZ":180,"scaleX":1,"scaleY":1,"scaleZ":1}},{"CardID":100,"Name":"Card","Nickname":"Mountain","Transform":{"posX":0,"posY":0,"posZ":0,"rotX":0,"rotY":180,"rotZ":180,"scaleX":1,"scaleY":1,"scaleZ":1}},{"CardID":200,"Name":"Card","Nickname":"Fervent Champion","Transform":{"posX":0,"posY":0,"posZ":0,"rotX":0,"rotY":180,"rotZ":180,"scaleX":1,"scaleY":1,"scaleZ":1}},{"CardID":200,"Name":"Card","Nickname":"Fervent Champion","Transform":{"posX":0,"posY":0,"posZ":0,"rotX":0,"rotY":180,"rotZ":180,"scaleX":1,"scaleY":1,"scaleZ":1}},{"CardID":200,"Name":"Card","Nickname":"Fervent Champion","Transform":{"posX":0,"posY":0,"posZ":0,"rotX":0,"rotY":180,"rotZ":180,"scaleX":1,"scaleY":1,"scaleZ":1}},{"CardID":200,"Name":"Card","Nickname":"Fervent Champion","Transform":{"posX":0,"posY":0,"posZ":0,"rotX":0,"rotY":180,"rotZ":180,"scaleX":1,"scaleY":1,"scaleZ":1}},{"CardID":300,"Name":"Card","Nickname":"Torbran, Thane of Red Fell","Transform":{"posX":0,"posY":0,"posZ":0,"rotX":0,"rotY":180,"rotZ":180,"scaleX":1,"scaleY":1,"scaleZ":1}},{"CardID":300,"Name":"Card","Nickname":"Torbran, Thane of Red Fell","Transform":{"posX":0,"posY":0,"posZ":0,"rotX":0,"rotY":180,"rotZ":180,"scaleX":1,"scaleY":1,"scaleZ":1}},{"CardID":300,"Name":"Card","Nickname":"Torbran, Thane of Red Fell","Transform":{"posX":0,"posY":0,"posZ":0,"rotX":0,"rotY":180,"rotZ":180,"scaleX":1,"scaleY":1,"scaleZ":1}},{"CardID":300,"Name":"Card","Nickname":"Torbran, Thane of Red Fell","Transform":{"posX":0,"posY":0,"posZ":0,"rotX":0,"rotY":180,"rotZ":180,"scaleX":1,"scaleY":1,"scaleZ":1}},{"CardID":400,"Name":"Card","Nickname":"Bonecrusher Giant // Stomp","Transform":{"posX":0,"posY":0,"posZ":0,"rotX":0,"rotY":180,"rotZ":180,"scaleX":1,"scaleY":1,"scaleZ":1}},{"CardID":400,"Name":"Card","Nickname":"Bonecrusher Giant // Stomp","Transform":{"posX":0,"posY":0,"posZ":0,"rotX":0,"rotY":180,"rotZ":180,"scaleX":1,"scaleY":1,"scaleZ":1}},{"CardID":400,"Name":"Card","Nickname":"Bonecrusher Giant // Stomp","Transform":{"posX":0,"posY":0,"posZ":0,"rotX":0,"rotY":180,"rotZ":180,"scaleX":1,"scaleY":1,"scaleZ":1}},{"CardID":400,"Name":"Card","Nickname":"Bonecrusher Giant // Stomp","Transform":{"posX":0,"posY":0,"posZ":0,"rotX":0,"rotY":180,"rotZ":180,"scaleX":1,"scaleY":1,"scaleZ":1}},{"CardID":500,"Name":"Card","Nickname":"Chandra, Acolyte of Flame","Transform":{"posX":0,"posY":0,"posZ":0,"rotX":0,"rotY":180,"rotZ":180,"scaleX":1,"scaleY":1,"scaleZ":1}},{"CardID":500,"Name":"Card","Nickname":"Chandra, Acolyte of Flame","Transform":{"posX":0,"posY":0,"posZ":0,"rotX":0,"rotY":180,"rotZ":180,"scaleX":1,"scaleY":1,"scaleZ":1}},{"CardID":500,"Name":"Card","Nickname":"Chandra, Acolyte of Flame","Transform":{"posX":0,"posY":0,"posZ":0,"rotX":0,"rotY":180,"rotZ":180,"scaleX":1,"scaleY":1,"scaleZ":1}},{"CardID":600,"Name":"Card","Nickname":"Light Up the Stage","Transform":{"posX":0,"posY":0,"posZ":0,"rotX":0,"rotY":180,"rotZ":180,"scaleX":1,"scaleY":1,"scaleZ":1}},{"CardID":600,"Name":"Card","Nickname":"Light Up the Stage","Transform":{"posX":0,"posY":0,"posZ":0,"rotX":0,"rotY":180,"rotZ":180,"scaleX":1,"scaleY":1,"scaleZ":1}},{"CardID":600,"Name":"Card","Nickname":"Light Up the Stage","Transform":{"posX":0,"posY":0,"posZ":0,"rotX":0,"rotY":180,"rotZ":180,"scaleX":1,"scaleY":1,"scaleZ":1}},{"CardID":600,"Name":"Card","Nickname":"Light Up the Stage","Transform":{"posX":0,"posY":0,"posZ":0,"rotX":0,"rotY":180,"rotZ":180,"scaleX":1,"scaleY":1,"scaleZ":1}},{"CardID":700,"Name":"Card","Nickname":"Embercleave","Transform":{"posX":0,"posY":0,"posZ":0,"rotX":0,"rotY":180,"rotZ":180,"scaleX":1,"scaleY":1,"scaleZ":1}},{"CardID":800,"Name":"Card","Nickname":"Castle Embereth","Transform":{"posX":0,"posY":0,"posZ":0,"rotX":0,"rotY":180,"rotZ":180,"scaleX":1,"scaleY":1,"scaleZ":1}},{"CardID":800,"Name":"Card","Nickname":"Castle Embereth","Transform":{"posX":0,"posY":0,"posZ":0,"rotX":0,"rotY":180,"rotZ":180,"scaleX":1,"scaleY":1,"scaleZ":1}},{"CardID":800,"Name":"Card","Nickname":"Castle Embereth","Transform":{"posX":0,"posY":0,"posZ":0,"rotX":0,"rotY":180,"rotZ":180,"scaleX":1,"scaleY":1,"scaleZ":1}},{"CardID":900,"Name":"Card","Nickname":"Rimrock Knight // Boulder Rush","Transform":{"posX":0,"posY":0,"posZ":0,"rotX":0,"rotY":180,"rotZ":180,"scaleX":1,"scaleY":1,"scaleZ":1}},{"CardID":900,"Name":"Card","Nickname":"Rimrock Knight // Boulder Rush","Transform":{"posX":0,"posY":0,"posZ":0,"rotX":0,"rotY":180,"rotZ":180,"scaleX":1,"scaleY":1,"scaleZ":1}},{"CardID":900,"Name":"Card","Nickname":"Rimrock Knight // Boulder Rush","Transform":{"posX":0,"posY":0,"posZ":0,"rotX":0,"rotY":180,"rotZ":180,"scaleX":1,"scaleY":1,"scaleZ":1}},{"CardID":900,"Name":"Card","Nickname":"Rimrock Knight // Boulder Rush","Transform":{"posX":0,"posY":0,"posZ":0,"rotX":0,"rotY":180,"rotZ":180,"scaleX":1,"scaleY":1,"scaleZ":1}},{"CardID":1000,"Name":"Card","Nickname":"Runaway Steam-Kin","Transform":{"posX":0,"posY":0,"posZ":0,"rotX":0,"rotY":180,"rotZ":180,"scaleX":1,"scaleY":1,"scaleZ":1}},{"CardID":1000,"Name":"Card","Nickname":"Runaway Steam-Kin","Transform":{"posX":0,"posY":0,"posZ":0,"rotX":0,"rotY":180,"rotZ":180,"scaleX":1,"scaleY":1,"scaleZ":1}},{"CardID":1000,"Name":"Card","Nickname":"Runaway Steam-Kin","Transform":{"posX":0,"posY":0,"posZ":0,"rotX":0,"rotY":180,"rotZ":180,"scaleX":1,"scaleY":1,"scaleZ":1}},{"CardID":1000,"Name":"Card","Nickname":"Runaway Steam-Kin","Transform":{"posX":0,"posY":0,"posZ":0,"rotX":0,"rotY":180,"rotZ":180,"scaleX":1,"scaleY":1,"scaleZ":1}},{"CardID":1100,"Name":"Card","Nickname":"Cavalcade of Calamity","Transform":{"posX":0,"posY":0,"posZ":0,"rotX":0,"rotY":180,"rotZ":180,"scaleX":1,"scaleY":1,"scaleZ":1}},{"CardID":1100,"Name":"Card","Nickname":"Cavalcade of Calamity","Transform":{"posX":0,"posY":0,"posZ":0,"rotX":0,"rotY":180,"rotZ":180,"scaleX":1,"scaleY":1,"scaleZ":1}},{"CardID":1100,"Name":"Card","Nickname":"Cavalcade of Calamity","Transform":{"posX":0,"posY":0,"posZ":0,"rotX":0,"rotY":180,"rotZ":180,"scaleX":1,"scaleY":1,"scaleZ":1}},{"CardID":1100,"Name":"Card","Nickname":"Cavalcade of Calamity","Transform":{"posX":0,"posY":0,"posZ":0,"rotX":0,"rotY":180,"rotZ":180,"scaleX":1,"scaleY":1,"scaleZ":1}},{"CardID":1200,"Name":"Card","Nickname":"Tin Street Dodger","Transform":{"posX":0,"posY":0,"posZ":0,"rotX":0,"rotY":180,"rotZ":180,"scaleX":1,"scaleY":1,"scaleZ":1}},{"CardID":1200,"Name":"Card","Nickname":"Tin Street Dodger","Transform":{"posX":0,"posY":0,"posZ":0,"rotX":0,"rotY":180,"rotZ":180,"scaleX":1,"scaleY":1,"scaleZ":1}},{"CardID":1200,"Name":"Card","Nickname":"Tin Street Dodger","Transform":{"posX":0,"posY":0,"posZ":0,"rotX":0,"rotY":180,"rotZ":180,"scaleX":1,"scaleY":1,"scaleZ":1}},{"CardID":1300,"Name":"Card","Nickname":"Scorch Spitter","Transform":{"posX":0,"posY":0,"posZ":0,"rotX":0,"rotY":180,"rotZ":180,"scaleX":1,"scaleY":1,"scaleZ":1}},{"CardID":1300,"Name":"Card","Nickname":"Scorch Spitter","Transform":{"posX":0,"posY":0,"posZ":0,"rotX":0,"rotY":180,"rotZ":180,"scaleX":1,"scaleY":1,"scaleZ":1}},{"CardID":1300,"Name":"Card","Nickname":"Scorch Spitter","Transform":{"posX":0,"posY":0,"posZ":0,"rotX":0,"rotY":180,"rotZ":180,"scaleX":1,"scaleY":1,"scaleZ":1}},{"CardID":1300,"Name":"Card","Nickname":"Scorch Spitter","Transform":{"posX":0,"posY":0,"posZ":0,"rotX":0,"rotY":180,"rotZ":180,"scaleX":1,"scaleY":1,"scaleZ":1}}],"DeckIDs":[100,100,100,100,100,100,100,100,100,100,100,100,100,100,100,100,100,100,200,200,200,200,300,300,300,300,400,400,400,400,500,500,500,600,600,600,600,700,800,800,800,900,900,900,900,1000,1000,1000,1000,1100,1100,1100,1100,1200,1200,1200,1300,1300,1300,1300],"CustomDeck":{"1":{"FaceURL":"https://www.frogtown.me/Images/V122/005a993c-5111-4364-9fba-75b3d94a8296.jpg","BackURL":"https://www.frogtown.me/CardBack.jpg","NumHeight":1,"NumWidth":1,"BackIsHidden":true},"2":{"FaceURL":"https://www.frogtown.me/Images/V122/01bf1bf8-1158-417b-946d-31af144b1b4c.jpg","BackURL":"https://www.frogtown.me/CardBack.jpg","NumHeight":1,"NumWidth":1,"BackIsHidden":true},"3":{"FaceURL":"https://www.frogtown.me/Images/V122/064ce69c-da9c-4d7b-8ec1-4ad300c011d1.jpg","BackURL":"https://www.frogtown.me/CardBack.jpg","NumHeight":1,"NumWidth":1,"BackIsHidden":true},"4":{"FaceURL":"https://www.frogtown.me/Images/V122/09fd2d9c-1793-4beb-a3fb-7a869f660cd4.jpg","BackURL":"https://www.frogtown.me/CardBack.jpg","NumHeight":1,"NumWidth":1,"BackIsHidden":true},"5":{"FaceURL":"https://www.frogtown.me/Images/V122/1b69993a-02ae-4eed-be6f-5682e2abb10e.jpg","BackURL":"https://www.frogtown.me/CardBack.jpg","NumHeight":1,"NumWidth":1,"BackIsHidden":true},"6":{"FaceURL":"https://www.frogtown.me/Images/V122/351de611-2162-4d3e-9080-ad29fb300243.jpg","BackURL":"https://www.frogtown.me/CardBack.jpg","NumHeight":1,"NumWidth":1,"BackIsHidden":true},"7":{"FaceURL":"https://www.frogtown.me/Images/V122/3e0838ff-8eb1-40ef-aee9-97cc52b5b8e0.jpg","BackURL":"https://www.frogtown.me/CardBack.jpg","NumHeight":1,"NumWidth":1,"BackIsHidden":true},"8":{"FaceURL":"https://www.frogtown.me/Images/V122/51d972cc-b08c-499c-a35e-51d275d5a4aa.jpg","BackURL":"https://www.frogtown.me/CardBack.jpg","NumHeight":1,"NumWidth":1,"BackIsHidden":true},"9":{"FaceURL":"https://www.frogtown.me/Images/V122/7111d244-9892-40f1-bb25-51521f51d46f.jpg","BackURL":"https://www.frogtown.me/CardBack.jpg","NumHeight":1,"NumWidth":1,"BackIsHidden":true},"10":{"FaceURL":"https://www.frogtown.me/Images/V122/849a9676-26d2-4cfd-8e3e-76c01db79398.jpg","BackURL":"https://www.frogtown.me/CardBack.jpg","NumHeight":1,"NumWidth":1,"BackIsHidden":true},"11":{"FaceURL":"https://www.frogtown.me/Images/V122/8a81e889-490b-4aeb-8e84-ea9a390bb8fe.jpg","BackURL":"https://www.frogtown.me/CardBack.jpg","NumHeight":1,"NumWidth":1,"BackIsHidden":true},"12":{"FaceURL":"https://www.frogtown.me/Images/V122/b3815ab6-87cd-4310-8068-ec721ee10a24.jpg","BackURL":"https://www.frogtown.me/CardBack.jpg","NumHeight":1,"NumWidth":1,"BackIsHidden":true},"13":{"FaceURL":"https://www.frogtown.me/Images/V122/bb701a84-24bd-41ed-9f06-25c8338902a5.jpg","BackURL":"https://www.frogtown.me/CardBack.jpg","NumHeight":1,"NumWidth":1,"BackIsHidden":true}},"Transform":{"posX":0,"posY":1,"posZ":0,"rotX":0,"rotY":180,"rotZ":180,"scaleX":1,"scaleY":1,"scaleZ":1}},{"Name":"Card","CustomDeck":{"1":{"FaceURL":"https://www.frogtown.me/Images/V122/fc7315d5-26d9-4ecc-bca2-b75c6fb12597.jpg","BackURL":"https://www.frogtown.me/CardBack.jpg","NumHeight":1,"NumWidth":1,"BackIsHidden":true}},"Transform":{"posX":2.2,"posY":1,"posZ":0,"rotX":0,"rotY":180,"rotZ":0,"scaleX":1,"scaleY":1,"scaleZ":1},"CardID":100,"Nickname":"Elemental"}]}