{"ObjectStates":[{"Name":"DeckCustom","ContainedObjects":[{"CardID":100,"Name":"Card","Nickname":"Phyrexian Tower","Transform":{"posX":0,"posY":0,"posZ":0,"rotX":0,"rotY":180,"rotZ":180,"scaleX":1,"scaleY":1,"scaleZ":1}},{"CardID":200,"Name":"Card","Nickname":"Forgotten Cave","Transform":{"posX":0,"posY":0,"posZ":0,"rotX":0,"rotY":180,"rotZ":180,"scaleX":1,"scaleY":1,"scaleZ":1}},{"CardID":300,"Name":"Card","Nickname":"Skirk Prospector","Transform":{"posX":0,"posY":0,"posZ":0,"rotX":0,"rotY":180,"rotZ":180,"scaleX":1,"scaleY":1,"scaleZ":1}},{"CardID":300,"Name":"Card","Nickname":"Skirk Prospector","Transform":{"posX":0,"posY":0,"posZ":0,"rotX":0,"rotY":180,"rotZ":180,"scaleX":1,"scaleY":1,"scaleZ":1}},{"CardID":300,"Name":"Card","Nickname":"Skirk Prospector","Transform":{"posX":0,"posY":0,"posZ":0,"rotX":0,"rotY":180,"rotZ":180,"scaleX":1,"scaleY":1,"scaleZ":1}},{"CardID":300,"Name":"Card","Nickname":"Skirk Prospector","Transform":{"posX":0,"posY":0,"posZ":0,"rotX":0,"rotY":180,"rotZ":180,"scaleX":1,"scaleY":1,"scaleZ":1}},{"CardID":400,"Name":"Card","Nickname":"Goblin Matron","Transform":{"posX":0,"posY":0,"posZ":0,"rotX":0,"rotY":180,"rotZ":180,"scaleX":1,"scaleY":1,"scaleZ":1}},{"CardID":400,"Name":"Card","Nickname":"Goblin Matron","Transform":{"posX":0,"posY":0,"posZ":0,"rotX":0,"rotY":180,"rotZ":180,"scaleX":1,"scaleY":1,"scaleZ":1}},{"CardID":400,"Name":"Card","Nickname":"Goblin Matron","Transform":{"posX":0,"posY":0,"posZ":0,"rotX":0,"rotY":180,"rotZ":180,"scaleX":1,"scaleY":1,"scaleZ":1}},{"CardID":400,"Name":"Card","Nickname":"Goblin Matron","Transform":{"posX":0,"posY":0,"posZ":0,"rotX":0,"rotY":180,"rotZ":180,"scaleX":1,"scaleY":1,"scaleZ":1}},{"CardID":500,"Name":"Card","Nickname":"Goblin Chieftain","Transform":{"posX":0,"posY":0,"posZ":0,"rotX":0,"rotY":180,"rotZ":180,"scaleX":1,"scaleY":1,"scaleZ":1}},{"CardID":500,"Name":"Card","Nickname":"Goblin Chieftain","Transform":{"posX":0,"posY":0,"posZ":0,"rotX":0,"rotY":180,"rotZ":180,"scaleX":1,"scaleY":1,"scaleZ":1}},{"CardID":500,"Name":"Card","Nickname":"Goblin Chieftain","Transform":{"posX":0,"posY":0,"posZ":0,"rotX":0,"rotY":180,"rotZ":180,"scaleX":1,"scaleY":1,"scaleZ":1}},{"CardID":500,"Name":"Card","Nickname":"Goblin Chieftain","Transform":{"posX":0,"posY":0,"posZ":0,"rotX":0,"rotY":180,"rotZ":180,"scaleX":1,"scaleY":1,"scaleZ":1}},{"CardID":600,"Name":"Card","Nickname":"Irencrag Feat","Transform":{"posX":0,"posY":0,"posZ":0,"rotX":0,"rotY":180,"rotZ":180,"scaleX":1,"scaleY":1,"scaleZ":1}},{"CardID":600,"Name":"Card","Nickname":"Irencrag Feat","Transform":{"posX":0,"posY":0,"posZ":0,"rotX":0,"rotY":180,"rotZ":180,"scaleX":1,"scaleY":1,"scaleZ":1}},{"CardID":600,"Name":"Card","Nickname":"Irencrag Feat","Transform":{"posX":0,"posY":0,"posZ":0,"rotX":0,"rotY":180,"rotZ":180,"scaleX":1,"scaleY":1,"scaleZ":1}},{"CardID":700,"Name":"Card","Nickname":"Muxus, Goblin Grandee","Transform":{"posX":0,"posY":0,"posZ":0,"rotX":0,"rotY":180,"rotZ":180,"scaleX":1,"scaleY":1,"scaleZ":1}},{"CardID":700,"Name":"Card","Nickname":"Muxus, Goblin Grandee","Transform":{"posX":0,"posY":0,"posZ":0,"rotX":0,"rotY":180,"rotZ":180,"scaleX":1,"scaleY":1,"scaleZ":1}},{"CardID":700,"Name":"Card","Nickname":"Muxus, Goblin Grandee","Transform":{"posX":0,"posY":0,"posZ":0,"rotX":0,"rotY":180,"rotZ":180,"scaleX":1,"scaleY":1,"scaleZ":1}},{"CardID":700,"Name":"Card","Nickname":"Muxus, Goblin Grandee","Transform":{"posX":0,"posY":0,"posZ":0,"rotX":0,"rotY":180,"rotZ":180,"scaleX":1,"scaleY":1,"scaleZ":1}},{"CardID":800,"Name":"Card","Nickname":"Krenko, Mob Boss","Transform":{"posX":0,"posY":0,"posZ":0,"rotX":0,"rotY":180,"rotZ":180,"scaleX":1,"scaleY":1,"scaleZ":1}},{"CardID":800,"Name":"Card","Nickname":"Krenko, Mob Boss","Transform":{"posX":0,"posY":0,"posZ":0,"rotX":0,"rotY":180,"rotZ":180,"scaleX":1,"scaleY":1,"scaleZ":1}},{"CardID":800,"Name":"Card","Nickname":"Krenko, Mob Boss","Transform":{"posX":0,"posY":0,"posZ":0,"rotX":0,"rotY":180,"rotZ":180,"scaleX":1,"scaleY":1,"scaleZ":1}},{"CardID":800,"Name":"Card","Nickname":"Krenko, Mob Boss","Transform":{"posX":0,"posY":0,"posZ":0,"rotX":0,"rotY":180,"rotZ":180,"scaleX":1,"scaleY":1,"scaleZ":1}},{"CardID":900,"Name":"Card","Nickname":"Castle Embereth","Transform":{"posX":0,"posY":0,"posZ":0,"rotX":0,"rotY":180,"rotZ":180,"scaleX":1,"scaleY":1,"scaleZ":1}},{"CardID":900,"Name":"Card","Nickname":"Castle Embereth","Transform":{"posX":0,"posY":0,"posZ":0,"rotX":0,"rotY":180,"rotZ":180,"scaleX":1,"scaleY":1,"scaleZ":1}},{"CardID":900,"Name":"Card","Nickname":"Castle Embereth","Transform":{"posX":0,"posY":0,"posZ":0,"rotX":0,"rotY":180,"rotZ":180,"scaleX":1,"scaleY":1,"scaleZ":1}},{"CardID":1000,"Name":"Card","Nickname":"Conspicuous Snoop","Transform":{"posX":0,"posY":0,"posZ":0,"rotX":0,"rotY":180,"rotZ":180,"scaleX":1,"scaleY":1,"scaleZ":1}},{"CardID":1000,"Name":"Card","Nickname":"Conspicuous Snoop","Transform":{"posX":0,"posY":0,"posZ":0,"rotX":0,"rotY":180,"rotZ":180,"scaleX":1,"scaleY":1,"scaleZ":1}},{"CardID":1000,"Name":"Card","Nickname":"Conspicuous Snoop","Transform":{"posX":0,"posY":0,"posZ":0,"rotX":0,"rotY":180,"rotZ":180,"scaleX":1,"scaleY":1,"scaleZ":1}},{"CardID":1000,"Name":"Card","Nickname":"Conspicuous Snoop","Transform":{"posX":0,"posY":0,"posZ":0,"rotX":0,"rotY":180,"rotZ":180,"scaleX":1,"scaleY":1,"scaleZ":1}},{"CardID":1100,"Name":"Card","Nickname":"Goblin Warchief","Transform":{"posX":0,"posY":0,"posZ":0,"rotX":0,"rotY":180,"rotZ":180,"scaleX":1,"scaleY":1,"scaleZ":1}},{"CardID":1100,"Name":"Card","Nickname":"Goblin Warchief","Transform":{"posX":0,"posY":0,"posZ":0,"rotX":0,"rotY":180,"rotZ":180,"scaleX":1,"scaleY":1,"scaleZ":1}},{"CardID":1100,"Name":"Card","Nickname":"Goblin Warchief","Transform":{"posX":0,"posY":0,"posZ":0,"rotX":0,"rotY":180,"rotZ":180,"scaleX":1,"scaleY":1,"scaleZ":1}},{"CardID":1100,"Name":"Card","Nickname":"Goblin Warchief","Transform":{"posX":0,"posY":0,"posZ":0,"rotX":0,"rotY":180,"rotZ":180,"scaleX":1,"scaleY":1,"scaleZ":1}},{"CardID":1200,"Name":"Card","Nickname":"Wily Goblin","Transform":{"posX":0,"posY":0,"posZ":0,"rotX":0,"rotY":180,"rotZ":180,"scaleX":1,"scaleY":1,"scaleZ":1}},{"CardID":1200,"Name":"Card","Nickname":"Wily Goblin","Transform":{"posX":0,"posY":0,"posZ":0,"rotX":0,"rotY":180,"rotZ":180,"scaleX":1,"scaleY":1,"scaleZ":1}},{"CardID":1200,"Name":"Card","Nickname":"Wily Goblin","Transform":{"posX":0,"posY":0,"posZ":0,"rotX":0,"rotY":180,"rotZ":180,"scaleX":1,"scaleY":1,"scaleZ":1}},{"CardID":1200,"Name":"Card","Nickname":"Wily Goblin","Transform":{"posX":0,"posY":0,"posZ":0,"rotX":0,"rotY":180,"rotZ":180,"scaleX":1,"scaleY":1,"scaleZ":1}},{"CardID":1300,"Name":"Card","Nickname":"Mountain","Transform":{"posX":0,"posY":0,"posZ":0,"rotX":0,"rotY":180,"rotZ":180,"scaleX":1,"scaleY":1,"scaleZ":1}},{"CardID":1300,"Name":"Card","Nickname":"Mountain","Transform":{"posX":0,"posY":0,"posZ":0,"rotX":0,"rotY":180,"rotZ":180,"scaleX":1,"scaleY":1,"scaleZ":1}},{"CardID":1300,"Name":"Card","Nickname":"Mountain","Transform":{"posX":0,"posY":0,"posZ":0,"rotX":0,"rotY":180,"rotZ":180,"scaleX":1,"scaleY":1,"scaleZ":1}},{"CardID":1300,"Name":"Card","Nickname":"Mountain","Transform":{"posX":0,"posY":0,"posZ":0,"rotX":0,"rotY":180,"rotZ":180,"scaleX":1,"scaleY":1,"scaleZ":1}},{"CardID":1300,"Name":"Card","Nickname":"Mountain","Transform":{"posX":0,"posY":0,"posZ":0,"rotX":0,"rotY":180,"rotZ":180,"scaleX":1,"scaleY":1,"scaleZ":1}},{"CardID":1300,"Name":"Card","Nickname":"Mountain","Transform":{"posX":0,"posY":0,"posZ":0,"rotX":0,"rotY":180,"rotZ":180,"scaleX":1,"scaleY":1,"scaleZ":1}},{"CardID":1300,"Name":"Card","Nickname":"Mountain","Transform":{"posX":0,"posY":0,"posZ":0,"rotX":0,"rotY":180,"rotZ":180,"scaleX":1,"scaleY":1,"scaleZ":1}},{"CardID":1300,"Name":"Card","Nickname":"Mountain","Transform":{"posX":0,"posY":0,"posZ":0,"rotX":0,"rotY":180,"rotZ":180,"scaleX":1,"scaleY":1,"scaleZ":1}},{"CardID":1300,"Name":"Card","Nickname":"Mountain","Transform":{"posX":0,"posY":0,"posZ":0,"rotX":0,"rotY":180,"rotZ":180,"scaleX":1,"scaleY":1,"scaleZ":1}},{"CardID":1300,"Name":"Card","Nickname":"Mountain","Transform":{"posX":0,"posY":0,"posZ":0,"rotX":0,"rotY":180,"rotZ":180,"scaleX":1,"scaleY":1,"scaleZ":1}},{"CardID":1300,"Name":"Card","Nickname":"Mountain","Transform":{"posX":0,"posY":0,"posZ":0,"rotX":0,"rotY":180,"rotZ":180,"scaleX":1,"scaleY":1,"scaleZ":1}},{"CardID":1300,"Name":"Card","Nickname":"Mountain","Transform":{"posX":0,"posY":0,"posZ":0,"rotX":0,"rotY":180,"rotZ":180,"scaleX":1,"scaleY":1,"scaleZ":1}},{"CardID":1300,"Name":"Card","Nickname":"Mountain","Transform":{"posX":0,"posY":0,"posZ":0,"rotX":0,"rotY":180,"rotZ":180,"scaleX":1,"scaleY":1,"scaleZ":1}},{"CardID":1300,"Name":"Card","Nickname":"Mountain","Transform":{"posX":0,"posY":0,"posZ":0,"rotX":0,"rotY":180,"rotZ":180,"scaleX":1,"scaleY":1,"scaleZ":1}},{"CardID":1300,"Name":"Card","Nickname":"Mountain","Transform":{"posX":0,"posY":0,"posZ":0,"rotX":0,"rotY":180,"rotZ":180,"scaleX":1,"scaleY":1,"scaleZ":1}},{"CardID":1300,"Name":"Card","Nickname":"Mountain","Transform":{"posX":0,"posY":0,"posZ":0,"rotX":0,"rotY":180,"rotZ":180,"scaleX":1,"scaleY":1,"scaleZ":1}},{"CardID":1300,"Name":"Card","Nickname":"Mountain","Transform":{"posX":0,"posY":0,"posZ":0,"rotX":0,"rotY":180,"rotZ":180,"scaleX":1,"scaleY":1,"scaleZ":1}},{"CardID":1300,"Name":"Card","Nickname":"Mountain","Transform":{"posX":0,"posY":0,"posZ":0,"rotX":0,"rotY":180,"rotZ":180,"scaleX":1,"scaleY":1,"scaleZ":1}},{"CardID":1300,"Name":"Card","Nickname":"Mountain","Transform":{"posX":0,"posY":0,"posZ":0,"rotX":0,"rotY":180,"rotZ":180,"scaleX":1,"scaleY":1,"scaleZ":1}},{"CardID":1300,"Name":"Card","Nickname":"Mountain","Transform":{"posX":0,"posY":0,"posZ":0,"rotX":0,"rotY":180,"rotZ":180,"scaleX":1,"scaleY":1,"scaleZ":1}}],"DeckIDs":[100,200,300,300,300,300,400,400,400,400,500,500,500,500,600,600,600,700,700,700,700,800,800,800,800,900,900,900,1000,1000,1000,1000,1100,1100,1100,1100,1200,1200,1200,1200,1300,1300,1300,1300,1300,1300,1300,1300,1300,1300,1300,1300,1300,1300,1300,1300,1300,1300,1300,1300],"CustomDeck":{"1":{"FaceURL":"https://www.frogtown.me/Images/V80/05b2cc68-1d20-421f-9800-af0996071554.jpg","BackURL":"https://www.frogtown.me/CardBack.jpg","NumHeight":1,"NumWidth":1,"BackIsHidden":true},"2":{"FaceURL":"https://www.frogtown.me/Images/V80/084bf9fe-78d2-4fef-8514-ed64d6c771e6.jpg","BackURL":"https://www.frogtown.me/CardBack.jpg","NumHeight":1,"NumWidth":1,"BackIsHidden":true},"3":{"FaceURL":"https://www.frogtown.me/Images/V80/1636d138-aa63-476f-a930-41b1be988032.jpg","BackURL":"https://www.frogtown.me/CardBack.jpg","NumHeight":1,"NumWidth":1,"BackIsHidden":true},"4":{"FaceURL":"https://www.frogtown.me/Images/V80/2092e6db-1196-43bf-b7c9-07498fa7ca90.jpg","BackURL":"https://www.frogtown.me/CardBack.jpg","NumHeight":1,"NumWidth":1,"BackIsHidden":true},"5":{"FaceURL":"https://www.frogtown.me/Images/V80/2540ec6b-9ffa-4ab0-bbd3-ddf1efd2db60.jpg","BackURL":"https://www.frogtown.me/CardBack.jpg","NumHeight":1,"NumWidth":1,"BackIsHidden":true},"6":{"FaceURL":"https://www.frogtown.me/Images/V80/257a84d3-bc4e-4bb3-a435-6d243929bd8c.jpg","BackURL":"https://www.frogtown.me/CardBack.jpg","NumHeight":1,"NumWidth":1,"BackIsHidden":true},"7":{"FaceURL":"https://www.frogtown.me/Images/V80/2c716d10-2130-43b7-a939-349d437e1091.jpg","BackURL":"https://www.frogtown.me/CardBack.jpg","NumHeight":1,"NumWidth":1,"BackIsHidden":true},"8":{"FaceURL":"https://www.frogtown.me/Images/V80/36aef540-1565-4f03-a01a-a51eb8cd1f0f.jpg","BackURL":"https://www.frogtown.me/CardBack.jpg","NumHeight":1,"NumWidth":1,"BackIsHidden":true},"9":{"FaceURL":"https://www.frogtown.me/Images/V80/51d972cc-b08c-499c-a35e-51d275d5a4aa.jpg","BackURL":"https://www.frogtown.me/CardBack.jpg","NumHeight":1,"NumWidth":1,"BackIsHidden":true},"10":{"FaceURL":"https://www.frogtown.me/Images/V80/5955db79-e235-41a8-b287-918551923e6c.jpg","BackURL":"https://www.frogtown.me/CardBack.jpg","NumHeight":1,"NumWidth":1,"BackIsHidden":true},"11":{"FaceURL":"https://www.frogtown.me/Images/V80/5a0d58e2-6755-42df-b7f6-aa87dc03c9fa.jpg","BackURL":"https://www.frogtown.me/CardBack.jpg","NumHeight":1,"NumWidth":1,"BackIsHidden":true},"12":{"FaceURL":"https://www.frogtown.me/Images/V80/a175b24c-c256-45a8-b24a-6b83e42d5efa.jpg","BackURL":"https://www.frogtown.me/CardBack.jpg","NumHeight":1,"NumWidth":1,"BackIsHidden":true},"13":{"FaceURL":"https://www.frogtown.me/Images/V80/ab92170a-0c92-4e48-8ed1-f93d2e08e842.jpg","BackURL":"https://www.frogtown.me/CardBack.jpg","NumHeight":1,"NumWidth":1,"BackIsHidden":true}},"Transform":{"posX":0,"posY":1,"posZ":0,"rotX":0,"rotY":180,"rotZ":180,"scaleX":1,"scaleY":1,"scaleZ":1}},{"Name":"DeckCustom","ContainedObjects":[{"CardID":100,"Name":"Card","Nickname":"Goblin","Transform":{"posX":0,"posY":0,"posZ":0,"rotX":0,"rotY":180,"rotZ":180,"scaleX":1,"scaleY":1,"scaleZ":1}},{"CardID":200,"Name":"Card","Nickname":"Treasure","Transform":{"posX":0,"posY":0,"posZ":0,"rotX":0,"rotY":180,"rotZ":180,"scaleX":1,"scaleY":1,"scaleZ":1}}],"DeckIDs":[100,200],"CustomDeck":{"1":{"FaceURL":"https://www.frogtown.me/Images/V80/ff1df646-52f5-4292-9fd5-5b8393f63931.jpg","BackURL":"https://www.frogtown.me/CardBack.jpg","NumHeight":1,"NumWidth":1,"BackIsHidden":true},"2":{"FaceURL":"https://www.frogtown.me/Images/V80/fa8bbe0c-3813-4e3f-9bcf-cffe4fed6341.jpg","BackURL":"https://www.frogtown.me/CardBack.jpg","NumHeight":1,"NumWidth":1,"BackIsHidden":true}},"Transform":{"posX":2.2,"posY":1,"posZ":0,"rotX":0,"rotY":180,"rotZ":0,"scaleX":1,"scaleY":1,"scaleZ":1}}]}